selenium_pagefactory_impl/__init__.py
selenium_pagefactory_impl/page_factory.py
selenium_pagefactory_impl-0.1.0.dist-info/METADATA
selenium_pagefactory_impl-0.1.0.dist-info/WHEEL
selenium_pagefactory_impl-0.1.0.dist-info/RECORD
