Metadata-Version: 2.1
Name: selenium-pagefactory-impl
Version: 0.1.0
Summary: A Selenium Page Factory implementation for Python
License: MIT
Author: naveens33
Author-email: naveensagayaselvaraj@gmail.com
Requires-Python: >=3.12,<4.0
Classifier: License :: OSI Approved :: MIT License
Classifier: Programming Language :: Python :: 3
Classifier: Programming Language :: Python :: 3.12
Requires-Dist: selenium (>=4.16.0,<5.0.0)
